hardocr/__init__.py
hardocr/dataset.py
hardocr/model.py
hardocr/utils.py
hardocr/modules/feature_extraction.py
hardocr/modules/prediction.py
hardocr/modules/sequence_modeling.py
hardocr/modules/transformation.py
hardocr-0.1.7.dist-info/LICENSE.md
hardocr-0.1.7.dist-info/METADATA
hardocr-0.1.7.dist-info/WHEEL
hardocr-0.1.7.dist-info/top_level.txt
hardocr-0.1.7.dist-info/RECORD
