Metadata-Version: 2.1
Name: hardocr
Version: 0.1.7
Summary: None
License-File: LICENSE.md
Requires-Dist: numpy
Requires-Dist: manuscript-ocr==0.1.6
Requires-Dist: torch
Requires-Dist: torchvision
Requires-Dist: pandas
Requires-Dist: opencv-python-headless
Requires-Dist: pillow
Requires-Dist: tqdm
Requires-Dist: pyyaml
Requires-Dist: natsort
Requires-Dist: albumentations
Requires-Dist: nltk
